mal/__init__.py
mal/anime.py
mal/base.py
mal/characters.py
mal/client.py
mal/connection.py
mal/endpoints.py
mal/enums.py
mal/forum.py
mal/genre.py
mal/manga.py
mal/py.typed
mal/titles.py
mal/typed.py
mal/utils.py
mal_api_py-0.10.1.dist-info/licenses/LICENSE
mal_api_py-0.10.1.dist-info/METADATA
mal_api_py-0.10.1.dist-info/WHEEL
mal_api_py-0.10.1.dist-info/top_level.txt
mal_api_py-0.10.1.dist-info/RECORD
