Metadata-Version: 2.4
Name: mal-api.py
Version: 0.10.1
Summary: A MyAnimeListAPI wrapper written in Python.
Home-page: https://github.com/Skylake-dev/mal.py
Author: Skylake-dev
License: MIT
Classifier: License :: OSI Approved :: MIT License
Classifier: Programming Language :: Python :: 3
Classifier: Programming Language :: Python :: 3.8
Classifier: Topic :: Software Development :: Libraries
Classifier: Typing :: Typed
Requires-Python: >=3.8.0
License-File: LICENSE
Requires-Dist: requests>=2.26
Requires-Dist: typing_extensions>=4.0.1
Provides-Extra: docs
Requires-Dist: sphinx==7.1.0; extra == "docs"
Requires-Dist: sphinx-rtd-theme==1.3.0; extra == "docs"
Dynamic: author
Dynamic: classifier
Dynamic: description
Dynamic: description-content-type
Dynamic: home-page
Dynamic: license
Dynamic: license-file
Dynamic: provides-extra
Dynamic: requires-dist
Dynamic: requires-python
Dynamic: summary
